locate_system_path/__init__.py
locate_system_path/locator.py
locate_system_path-0.0.0.dist-info/METADATA
locate_system_path-0.0.0.dist-info/WHEEL
locate_system_path-0.0.0.dist-info/licenses/LICENSE
locate_system_path-0.0.0.dist-info/RECORD
