Metadata-Version: 2.1
Name: locate_system_path
Version: 0.0.0
Summary: This package makes a sys.path.append to run python files from console.
Project-URL: Repo Link, https://github.com/moralesveratom/locate-system-path
Author-email: Tomas Morales Vera <moralesveratomas@gmail.com>
License-File: LICENSE
Classifier: License :: OSI Approved :: MIT License
Classifier: Operating System :: OS Independent
Classifier: Programming Language :: Python :: 3
Requires-Python: >=3.7
